{
  "name": "UpSqllist",
  "fields": [
    {
      "fieldName": "build",
      "fieldType": "Long",
      "fieldValidateRules": ["required"]
    },
    {
      "fieldName": "sqlNo",
      "fieldType": "Long",
      "fieldValidateRules": ["required"]
    },
    {
      "fieldName": "sqltext",
      "fieldType": "String",
      "fieldValidateRules": ["maxlength"],
      "fieldValidateRulesMaxlength": "2000"
    },
    {
      "fieldName": "runsign",
      "fieldType": "Long"
    },
    {
      "fieldName": "optime",
      "fieldType": "Instant"
    },
    {
      "fieldName": "errtext",
      "fieldType": "String",
      "fieldValidateRules": ["maxlength"],
      "fieldValidateRulesMaxlength": "1000"
    }
  ],
  "relationships": [],
  "entityTableName": "up_sqllist",
  "dto": "mapstruct",
  "pagination": "pagination",
  "service": "serviceClass",
  "jpaMetamodelFiltering": true,
  "fluentMethods": true,
  "readOnly": false,
  "embedded": false,
  "applications": "*",
  "changelogDate": "20210401131616"
}
